{"word_list":[{"word":"\u732b","reading":"\u306d\u3053","meaning":"cat"},{"word":"\u4f1a","reading":"\u3048","meaning":"gathering (esp. Buddhist, festive, etc.)"},{"word":"\u8089","reading":"\u306b\u304f","meaning":"flesh"},{"word":"\u9ce5","reading":"\u3068\u308a","meaning":"bird"},{"word":"\u85ac","reading":"\u304f\u3059\u308a","meaning":"medicine"},{"word":"\u5341","reading":"\u3058\u3085\u3046","meaning":"10"},{"word":"\u897f","reading":"\u306b\u3057","meaning":"west"},{"word":"\u65e5","reading":"\u3072","meaning":"day"},{"word":"\u4e8c","reading":"\u306b","meaning":"two"},{"word":"\u6cf3\u3050","reading":"\u304a\u3088\u3050","meaning":"to swim"},{"word":"\u9ce5\u8089","reading":"\u3068\u308a\u306b\u304f","meaning":"chicken meat"},{"word":"\u4e8c\u5341","reading":"\u306b\u3058\u3085\u3046","meaning":"twenty"},{"word":"\u897f\u65e5","reading":"\u306b\u3057\u3073","meaning":"westering sun"},{"word":"\u4e8c\u65e5","reading":"\u3075\u3064\u304b","meaning":"second day of the month"},{"word":"\u5341\u85ac","reading":"\u3069\u304f\u3060\u307f","meaning":"chameleon plant (Houttuynia cordata)"},{"word":"\u65e5\u897f","reading":"\u306b\u3063\u305b\u3044","meaning":"Japanese-Spanish (gen. for translations and dictionaries)"},{"word":"\u4f1a\u3046","reading":"\u3042\u3046","meaning":"to meet"},{"word":"\u5341\u4e8c","reading":"\u3058\u3085\u3046\u306b","meaning":"12"},{"word":"\u5341\u65e5","reading":"\u3068\u304a\u304b","meaning":"the tenth day of the month"},{"word":"\u547c\u3076","reading":"\u3088\u3076","meaning":"to call out (to)"},{"word":"\u6691\u3044","reading":"\u3042\u3064\u3044","meaning":"hot (weather, etc.)"},{"word":"\u4e8c\u5341\u65e5","reading":"\u306f\u3064\u304b","meaning":"twentieth day of the month"}],"character_list":["\u4e8c","\u5341","\u65e5","\u6cf3","\u3050","\u732b","\u8089","\u85ac","\u4f1a","\u3046","\u547c","\u3076","\u9ce5","\u6691","\u3044","\u897f"]}
