{"word_list":[{"word":"\u773c","reading":"\u3081","meaning":"eye"},{"word":"\u4e00","reading":"\u3044\u3061","meaning":"one"},{"word":"\u6c60","reading":"\u3044\u3051","meaning":"pond"},{"word":"\u82e5","reading":"\u308f\u304b","meaning":"youth"},{"word":"\u5927","reading":"\u304a\u304a","meaning":"big"},{"word":"\u5b66","reading":"\u304c\u304f","meaning":"learning"},{"word":"\u697d","reading":"\u3089\u304f","meaning":"comfort"},{"word":"\u93e1","reading":"\u304b\u304c\u307f","meaning":"mirror"},{"word":"\u53e3","reading":"\u304f\u3061","meaning":"mouth"},{"word":"\u7dd2","reading":"\u3044\u3068\u3050\u3061","meaning":"thread end"},{"word":"\u4e03","reading":"\u3057\u3061","meaning":"seven"},{"word":"\u97f3","reading":"\u304a\u3068","meaning":"sound"},{"word":"\u5165","reading":"\u3044\u308a","meaning":"entering"},{"word":"\u4e00\u773c","reading":"\u3044\u3061\u304c\u3093","meaning":"one eye"},{"word":"\u82e5\u3044","reading":"\u308f\u304b\u3044","meaning":"young"},{"word":"\u773c\u93e1","reading":"\u3081\u304c\u306d","meaning":"spectacles"},{"word":"\u5165\u5b66","reading":"\u306b\u3085\u3046\u304c\u304f","meaning":"entry to school or university"},{"word":"\u5927\u5b66","reading":"\u3060\u3044\u304c\u304f","meaning":"post-secondary education institution, incl. university, college, etc."},{"word":"\u97f3\u5927","reading":"\u304a\u3093\u3060\u3044","meaning":"college of music"},{"word":"\u5927\u53e3","reading":"\u304a\u304a\u3050\u3061","meaning":"big mouth"},{"word":"\u697d\u97f3","reading":"\u304c\u304f\u304a\u3093","meaning":"musical note"},{"word":"\u97f3\u697d","reading":"\u304a\u3093\u304c\u304f","meaning":"music"},{"word":"\u5f15\u304f","reading":"\u3072\u304f","meaning":"to pull"},{"word":"\u5165\u53e3","reading":"\u3044\u308a\u3050\u3061","meaning":"entrance"},{"word":"\u82e5\u304f","reading":"\u3057\u304f","meaning":"to match"},{"word":"\u4e00\u5165","reading":"\u3072\u3068\u3057\u304a","meaning":"still more"},{"word":"\u5927\u3044","reading":"\u304a\u304a\u3044","meaning":"greater (of equal court ranks)"},{"word":"\u4e00\u5927","reading":"\u3044\u3061\u3060\u3044","meaning":"one large ..."},{"word":"\u4e00\u53e3","reading":"\u3072\u3068\u304f\u3061","meaning":"mouthful"},{"word":"\u4e00\u7dd2","reading":"\u3044\u3063\u3057\u3087","meaning":"together"},{"word":"\u53e3\u97f3","reading":"\u3053\u3046\u304a\u3093","meaning":"oral consonant"},{"word":"\u97f3\u697d\u5b66","reading":"\u304a\u3093\u304c\u304f\u304c\u304f","meaning":"musicology"},{"word":"\u97f3\u697d\u5927\u5b66","reading":"\u304a\u3093\u304c\u304f\u3060\u3044\u304c\u304f","meaning":"College of Music"}],"character_list":["\u5f15","\u304f","\u5165","\u53e3","\u773c","\u93e1","\u5927","\u5b66","\u82e5","\u3044","\u97f3","\u697d","\u4e00","\u7dd2","\u4e03","\u6c60"]}
