{"word_list":[{"word":"\u6a4b","reading":"\u306f\u3057","meaning":"bridge"},{"word":"\u9031","reading":"\u3057\u3085\u3046","meaning":"week"},{"word":"\u96ea","reading":"\u3086\u304d","meaning":"snow"},{"word":"\u9ce5","reading":"\u3068\u308a","meaning":"bird"},{"word":"\u65b0","reading":"\u3057\u3093","meaning":"new"},{"word":"\u5148","reading":"\u3055\u304d","meaning":"previous"},{"word":"\u52e2","reading":"\u305b\u3044","meaning":"energy"},{"word":"\u7537","reading":"\u304a\u3068\u3053","meaning":"man"},{"word":"\u96e8","reading":"\u3042\u3081","meaning":"rain"},{"word":"\u51fa","reading":"\u3067","meaning":"coming out"},{"word":"\u5927","reading":"\u304a\u304a","meaning":"big"},{"word":"\u5927\u7537","reading":"\u304a\u304a\u304a\u3068\u3053","meaning":"great man"},{"word":"\u65b0\u6a4b","reading":"\u3057\u3093\u3070\u3057","meaning":"Shinbashi (section of Tokyo)"},{"word":"\u51fa\u5148","reading":"\u3067\u3055\u304d","meaning":"one's destination"},{"word":"\u51fa\u308b","reading":"\u3067\u308b","meaning":"to go out"},{"word":"\u96e8\u7537","reading":"\u3042\u3081\u304a\u3068\u3053","meaning":"man whose presence seems to cause rain"},{"word":"\u5927\u96ea","reading":"\u304a\u304a\u3086\u304d","meaning":"heavy snow"},{"word":"\u5927\u96e8","reading":"\u304a\u304a\u3042\u3081","meaning":"heavy rain"},{"word":"\u5148\u9031","reading":"\u305b\u3093\u3057\u3085\u3046","meaning":"last week"},{"word":"\u96e8\u9ce5","reading":"\u3042\u307e\u3069\u308a","meaning":"fork-tailed swift (Apus pacificus)"},{"word":"\u5927\u9ce5","reading":"\u304a\u304a\u3068\u308a","meaning":"large bird"},{"word":"\u5148\u51fa","reading":"\u305b\u3093\u3057\u3085\u3064","meaning":"aforementioned"},{"word":"\u52e2\u3044","reading":"\u3044\u304d\u304a\u3044","meaning":"force"},{"word":"\u5927\u3044","reading":"\u304a\u304a\u3044","meaning":"greater (of equal court ranks)"},{"word":"\u65b0\u96ea","reading":"\u3057\u3093\u305b\u3064","meaning":"new snow"},{"word":"\u96ea\u7537","reading":"\u3086\u304d\u304a\u3068\u3053","meaning":"abominable snowman"},{"word":"\u5927\u52e2","reading":"\u304a\u304a\u305c\u3044","meaning":"many"},{"word":"\u51fa\u3057","reading":"\u3060\u3057","meaning":"dashi (Japanese soup stock made from fish and kelp)"},{"word":"\u65b0\u3057\u3044","reading":"\u3042\u305f\u3089\u3057\u3044","meaning":"new"},{"word":"\u5148\u51fa\u3057","reading":"\u3055\u304d\u3060\u3057","meaning":"first out"},{"word":"\u5927\u3057\u3051","reading":"\u304a\u304a\u3057\u3051","meaning":"very stormy weather (at sea)"},{"word":"\u6a4b\u304b\u3051","reading":"\u306f\u3057\u304b\u3051","meaning":"bridge building"},{"word":"\u304b\u3051\u6a4b","reading":"\u304b\u3051\u306f\u3057","meaning":"suspension bridge"},{"word":"\u51fa\u304b\u3051\u308b","reading":"\u3067\u304b\u3051\u308b","meaning":"to depart"}],"character_list":["\u51fa","\u304b","\u3051","\u308b","\u9ce5","\u7537","\u96e8","\u96ea","\u5148","\u9031","\u5927","\u52e2","\u6a4b","\u65b0","\u3057","\u3044"]}
