{"word_list":[{"word":"\u5348","reading":"\u3046\u307e","meaning":"seventh sign of Chinese zodiac (The Horse, 11am-1pm, south, May)"},{"word":"\u6b21","reading":"\u3064\u304e","meaning":"next"},{"word":"\u5acc","reading":"\u3044\u3084","meaning":"disagreeable"},{"word":"\u4eca","reading":"\u3044\u307e","meaning":"now"},{"word":"\u8cea","reading":"\u3057\u3064","meaning":"quality"},{"word":"\u984c","reading":"\u3060\u3044","meaning":"title"},{"word":"\u5f8c","reading":"\u3042\u3068","meaning":"behind"},{"word":"\u554f","reading":"\u3068\u3044","meaning":"question"},{"word":"\u5869","reading":"\u3057\u304a","meaning":"salt (i.e. sodium chloride)"},{"word":"\u6687","reading":"\u3072\u307e","meaning":"spare time"},{"word":"\u7d42","reading":"\u304a\u308f\u308a","meaning":"the end"},{"word":"\u7d42\u308b","reading":"\u304a\u308f\u308b","meaning":"to finish"},{"word":"\u7d42\u3044","reading":"\u3057\u307e\u3044","meaning":"end"},{"word":"\u958b\u304f","reading":"\u3072\u3089\u304f","meaning":"to open (e.g. a bank-account, festival, etc.)"},{"word":"\u554f\u3044","reading":"\u3068\u3044","meaning":"question"},{"word":"\u4eca\u6b21","reading":"\u3053\u3093\u3058","meaning":"the present time"},{"word":"\u4eca\u5f8c","reading":"\u3053\u3093\u3054","meaning":"from now on"},{"word":"\u5acc\u3044","reading":"\u304d\u3089\u3044","meaning":"dislike"},{"word":"\u8cea\u554f","reading":"\u3057\u3064\u3082\u3093","meaning":"question"},{"word":"\u5348\u5f8c","reading":"\u3054\u3054","meaning":"afternoon"},{"word":"\u8d70\u308b","reading":"\u306f\u3057\u308b","meaning":"to run"},{"word":"\u554f\u984c","reading":"\u3082\u3093\u3060\u3044","meaning":"problem"}],"character_list":["\u958b","\u304f","\u7d42","\u308b","\u8cea","\u554f","\u6b21","\u5acc","\u3044","\u5869","\u4eca","\u984c","\u5348","\u5f8c","\u8d70","\u6687"]}
